Metadata-Version: 2.1
Name: guia_cli
Version: 0.0.10
Summary: Gu, a simple IA agent that specializes in software engineering, aiding in coding tasks and providing technical guidance.
Home-page: https://github.com/andersonbosa/guia-cli
Author: Anderson Bosa
License: CC0-1.0
Keywords: IA assistant gemini-pro
Classifier: Development Status :: 3 - Alpha
Classifier: Environment :: Console
Classifier: License :: OSI Approved :: MIT License
Classifier: Intended Audience :: Developers
Classifier: Intended Audience :: Science/Research
Classifier: Intended Audience :: End Users/Desktop
Classifier: Operating System :: OS Independent
Classifier: Programming Language :: Python
Classifier: Topic :: Scientific/Engineering :: Artificial Intelligence
Requires-Python: >=3.10
License-File: LICENSE.md
Requires-Dist: crewai>=0.19.0
Requires-Dist: langchain_google_genai
Requires-Dist: python-dotenv>=1.0.1
